{
  "simulation": {
    "duration_days": 30,
    "time_step_minutes": 60,
    "season": "Winter",
    "start_date": "2026-06-01"
  },
  "battery": {
    "capacity": 13.5,
    "initial_state": 0.0,
    "efficiency": 0.90,
    "discharge_depth": 0.05
  },
  "solar": {
    "panel_peak_kw": 5.0,
    "inverter_max_kw": 4.0,
    "inverter_failure_rate": 0.005,
    "failure_duration_min_hours": 4,
    "failure_duration_max_hours": 72
  },
  "load": {
    "base_load_kw": 0.5,
    "peak_load_kw": 3.0,
    "peak_start_hour": 18,
    "peak_end_hour": 21
  },
  "grid": {
    "export_limit_kw": 20.0,
    "cost_import_cents": 75,
    "price_export_cents": 90
  },
  "strategy": {
    "name": "LOAD_PRIORITY"
  }
}